py_rql/__init__.py
py_rql/cast.py
py_rql/constants.py
py_rql/exceptions.py
py_rql/filter_cls.py
py_rql/grammar.py
py_rql/helpers.py
py_rql/operators.py
py_rql/parser.py
py_rql/transformer.py
lib_rql-2.0.1.dist-info/LICENSE
lib_rql-2.0.1.dist-info/METADATA
lib_rql-2.0.1.dist-info/WHEEL
lib_rql-2.0.1.dist-info/RECORD
