Metadata-Version: 2.1
Name: lib-rql
Version: 2.0.1
Summary: Python RQL Filtering
Home-page: https://connect.cloudblue.com/community/api/rql/
License: Apache-2.0
Keywords: rql,filter
Author: CloudBlue LLC
Requires-Python: >=3.8,<4
Classifier: Development Status :: 5 - Production/Stable
Classifier: Intended Audience :: Developers
Classifier: License :: OSI Approved :: Apache Software License
Classifier: Operating System :: Unix
Classifier: Programming Language :: Python :: 3
Classifier: Programming Language :: Python :: 3.8
Classifier: Programming Language :: Python :: 3.9
Classifier: Programming Language :: Python :: 3.10
Classifier: Programming Language :: Python :: 3.11
Classifier: Programming Language :: Python :: 3.12
Classifier: Topic :: Text Processing :: Filters
Requires-Dist: cachetools (>=4.2.4)
Requires-Dist: lark-parser (==0.11.0)
Requires-Dist: python-dateutil (>=2.8.2)
Project-URL: Repository, https://github.com/cloudblue/lib-rql
